xiang/__init__.py
xiang/cli.py
xiang/converter.py
xlsxtofits-1.0.0.dist-info/COPYING
xlsxtofits-1.0.0.dist-info/LICENSE
xlsxtofits-1.0.0.dist-info/METADATA
xlsxtofits-1.0.0.dist-info/WHEEL
xlsxtofits-1.0.0.dist-info/entry_points.txt
xlsxtofits-1.0.0.dist-info/top_level.txt
xlsxtofits-1.0.0.dist-info/RECORD
